nwbinspector/__init__.py
nwbinspector/_configuration.py
nwbinspector/_dandi_inspection.py
nwbinspector/_formatting.py
nwbinspector/_nwb_inspection.py
nwbinspector/_nwbinspector_cli.py
nwbinspector/_organization.py
nwbinspector/_registration.py
nwbinspector/_types.py
nwbinspector/_internal_configs/config.schema.json
nwbinspector/_internal_configs/dandi.inspector_config.yaml
nwbinspector/checks/__init__.py
nwbinspector/checks/_behavior.py
nwbinspector/checks/_ecephys.py
nwbinspector/checks/_general.py
nwbinspector/checks/_icephys.py
nwbinspector/checks/_image_series.py
nwbinspector/checks/_images.py
nwbinspector/checks/_nwb_containers.py
nwbinspector/checks/_nwbfile_metadata.py
nwbinspector/checks/_ogen.py
nwbinspector/checks/_ophys.py
nwbinspector/checks/_tables.py
nwbinspector/checks/_time_series.py
nwbinspector/checks/behavior/__init__.py
nwbinspector/checks/ecephys/__init__.py
nwbinspector/checks/general/__init__.py
nwbinspector/checks/icephys/__init__.py
nwbinspector/checks/image_series/__init__.py
nwbinspector/checks/images/__init__.py
nwbinspector/checks/nwb_containers/__init__.py
nwbinspector/checks/nwbfile_metadata/__init__.py
nwbinspector/checks/ogen/__init__.py
nwbinspector/checks/ophys/__init__.py
nwbinspector/checks/tables/__init__.py
nwbinspector/checks/time_series/__init__.py
nwbinspector/inspector_tools/__init__.py
nwbinspector/nwbinspector/__init__.py
nwbinspector/register_checks/__init__.py
nwbinspector/testing/__init__.py
nwbinspector/testing/_testing.py
nwbinspector/tools/__init__.py
nwbinspector/tools/_dandi.py
nwbinspector/tools/_nwb.py
nwbinspector/tools/_read_nwbfile.py
nwbinspector/tools/dandi/__init__.py
nwbinspector/tools/nwb/__init__.py
nwbinspector/utils/__init__.py
nwbinspector/utils/_utils.py
nwbinspector/version/__init__.py
nwbinspector-0.6.5.dist-info/METADATA
nwbinspector-0.6.5.dist-info/WHEEL
nwbinspector-0.6.5.dist-info/entry_points.txt
nwbinspector-0.6.5.dist-info/RECORD
