Metadata-Version: 2.4
Name: nwbinspector
Version: 0.6.5
Summary: Tool to inspect NWB files for best practices compliance.
Project-URL: Homepage, https://github.com/NeurodataWithoutBorders/nwbinspector
Author: Cody Baker, Steph Prince, Szonja Weigl, Heberto Mayorquin, Paul Adkisson, Luiz Tauffer, Ryan Ly
Author-email: Ben Dichter <ben.dichter@catalystneuro.com>
License: “nwbinspector” Copyright (c) 2022-2025, The Regents of the University of California, through Lawrence Berkeley National Laboratory (subject to receipt of any required approvals from the U.S. Dept. of Energy).  All rights reserved.
Keywords: nwb
Classifier: Intended Audience :: Science/Research
Classifier: License :: OSI Approved :: BSD License
Classifier: Operating System :: MacOS
Classifier: Operating System :: Microsoft :: Windows
Classifier: Operating System :: POSIX :: Linux
Classifier: Programming Language :: Python :: 3.9
Classifier: Programming Language :: Python :: 3.10
Classifier: Programming Language :: Python :: 3.11
Classifier: Programming Language :: Python :: 3.12
Classifier: Programming Language :: Python :: 3.13
Requires-Python: >=3.9
Requires-Dist: aiohttp
Requires-Dist: click
Requires-Dist: fsspec
Requires-Dist: hdmf-zarr
Requires-Dist: isodate
Requires-Dist: jsonschema
Requires-Dist: natsort
Requires-Dist: packaging
Requires-Dist: pynwb>=3.1
Requires-Dist: pyyaml
Requires-Dist: requests
Requires-Dist: tqdm
Provides-Extra: dandi
Requires-Dist: dandi; extra == 'dandi'
Requires-Dist: remfile; extra == 'dandi'
